synapx/__init__.py
synapx/_C/__init__.pyi
synapx/_C/_nn.pyi
synapx/include/synapx/core.hpp
synapx/include/synapx/functional.hpp
synapx/include/synapx/synapx.hpp
synapx/include/synapx/tensor.hpp
synapx/include/synapx/autograd/engine.hpp
synapx/include/synapx/autograd/functions.hpp
synapx/include/synapx/autograd/graph.hpp
synapx/include/synapx/autograd/utils.hpp
synapx/lib/libtorch-2.4.X/_C.cp311-win_amd64.pyd
synapx/lib/libtorch-2.4.X/synapx.dll
synapx/lib/libtorch-2.4.X/synapx.lib
synapx/lib/libtorch-2.5.X/_C.cp311-win_amd64.pyd
synapx/lib/libtorch-2.5.X/synapx.dll
synapx/lib/libtorch-2.5.X/synapx.lib
synapx/lib/libtorch-2.6.X/_C.cp311-win_amd64.pyd
synapx/lib/libtorch-2.6.X/synapx.dll
synapx/lib/libtorch-2.6.X/synapx.lib
synapx/lib/libtorch-2.7.X/_C.cp311-win_amd64.pyd
synapx/lib/libtorch-2.7.X/synapx.dll
synapx/lib/libtorch-2.7.X/synapx.lib
synapx/nn/__init__.py
synapx/nn/activations.py
synapx/nn/functional.py
synapx/nn/init.py
synapx/nn/layers.py
synapx/nn/losses.py
synapx/nn/modules.py
synapx/optim/__init__.py
synapx/optim/optimizers.py
synapx/share/cmake/synapx/SynapxConfig.cmake
synapx/share/cmake/synapx/SynapxConfigVersion.cmake
synapx-0.1.0.dist-info/licenses/LICENSE
synapx-0.1.0.dist-info/METADATA
synapx-0.1.0.dist-info/WHEEL
synapx-0.1.0.dist-info/top_level.txt
synapx-0.1.0.dist-info/RECORD
