Metadata-Version: 2.4
Name: synapx
Version: 0.1.0
Summary: A deep learning library powered by a C++ autograd engine, featuring a PyTorch-like API and cross-platform support.
Author-email: Pablo García Mesa <pgmesa.sm@gmail.com>
License-Expression: MIT
Project-URL: Homepage, https://github.com/pgmesa/synapx
Keywords: Autograd,Tensor,Machine Learning,Deep Learning,C++,Python
Classifier: Development Status :: 3 - Alpha
Classifier: Intended Audience :: Developers
Classifier: Intended Audience :: Education
Classifier: Intended Audience :: Science/Research
Classifier: Operating System :: Microsoft :: Windows
Classifier: Operating System :: POSIX :: Linux
Classifier: Programming Language :: C++
Classifier: Programming Language :: Python :: 3
Classifier: Programming Language :: Python :: 3.9
Classifier: Programming Language :: Python :: 3.10
Classifier: Programming Language :: Python :: 3.11
Classifier: Programming Language :: Python :: 3.12
Classifier: Topic :: Scientific/Engineering
Classifier: Topic :: Scientific/Engineering :: Mathematics
Classifier: Topic :: Scientific/Engineering :: Artificial Intelligence
Classifier: Topic :: Software Development
Classifier: Topic :: Software Development :: Libraries
Classifier: Topic :: Software Development :: Libraries :: Python Modules
Requires-Python: <3.13,>=3.9
License-File: LICENSE
Requires-Dist: torch<=2.7.0,>=2.4.0; python_version == "3.9"
Requires-Dist: torch<=2.7.0,>=2.4.0; python_version == "3.10"
Requires-Dist: torch<=2.7.0,>=2.4.0; python_version == "3.11"
Requires-Dist: torch<=2.7.0,>=2.4.0; python_version == "3.12"
Provides-Extra: build
Requires-Dist: pybind11<3.0.0,>=2.6.0; extra == "build"
Requires-Dist: pybind11-stubgen<3.0.0,>=2.0.0; extra == "build"
Dynamic: license-file
